mmary_calculator_package/__init__.py
mmary_calculator_package/accessor.py
mmary_calculator_package/calculator.py
mmary_calculator_package/contracts.py
mmary_calculator_package/custom_types.py
mmary_calculator_package/dto.py
mmary_calculator_package/enums.py
mmary_calculator_package-0.0.1.dist-info/METADATA
mmary_calculator_package-0.0.1.dist-info/WHEEL
mmary_calculator_package-0.0.1.dist-info/licenses/LICENSE
mmary_calculator_package-0.0.1.dist-info/RECORD
